mip_tool/__init__.py
mip_tool/py.typed
mip_tool/util.py
mip_tool/func/__init__.py
mip_tool/view/__init__.py
mip_tool/view/__main__.py
mip_tool-0.6.4.dist-info/METADATA
mip_tool-0.6.4.dist-info/WHEEL
mip_tool-0.6.4.dist-info/entry_points.txt
mip_tool-0.6.4.dist-info/licenses/LICENSE
mip_tool-0.6.4.dist-info/RECORD
