Metadata-Version: 2.3
Name: mip-tool
Version: 0.6.4
Summary: `mip-tool` is a package for Python-MIP.
Project-URL: homepage, https://github.com/SaitoTsutomu/mip-tool
Author-email: Saito Tsutomu <tsutomu7@hotmail.co.jp>
License: Apache-2.0
License-File: LICENSE
Classifier: Development Status :: 1 - Planning
Classifier: License :: OSI Approved :: Apache Software License
Classifier: Programming Language :: Python
Classifier: Topic :: Scientific/Engineering
Classifier: Topic :: Software Development
Requires-Python: >=3.11
Requires-Dist: mip>=1.14.2
Requires-Dist: pandas>=2.2.3
Provides-Extra: pulp
Requires-Dist: pulp; extra == 'pulp'
